novel3/__init__.py
novel3/novel_yunlin/__init__.py
novel3/novel_yunlin/config.py
novel3/novel_yunlin/file_change_to_db.py
novel3/novel_yunlin/image_to_str_map.py
novel3/novel_yunlin/spider.py
novel3/novel_yunlin/web.py
novel3/novel_yunlin/yun_lin_zhan_ye_scrapy.py
novel3/novel_yunlin/config/mysql.json
novel3/novel_yunlin/config/novel.json
novel3/novel_yunlin/config/sqlite.json
novel3/novel_yunlin/db/__init__.py
novel3/novel_yunlin/db/mysql.py
novel3/novel_yunlin/db/sqlite.py
novel3/novel_yunlin/json/illegal.json
novel3/novel_yunlin/json/illegal_chapter_name.json
novel3/novel_yunlin/json/image_str.json
novel3/novel_yunlin/sql/mysql/book.sql
novel3/novel_yunlin/sql/mysql/chapter.sql
novel3/novel_yunlin/sql/sqlite/book.sql
novel3/novel_yunlin/sql/sqlite/chapter.sql
novel3/novel_yunlin/templates/novel.html
novel3/novel_yunlin/utils/__init__.py
novel3/novel_yunlin/utils/regex.py
novel3-0.0.31.dist-info/LICENSE.txt
novel3-0.0.31.dist-info/METADATA
novel3-0.0.31.dist-info/WHEEL
novel3-0.0.31.dist-info/top_level.txt
novel3-0.0.31.dist-info/RECORD
