Metadata-Version: 2.1
Name: novel3
Version: 0.0.31
Summary: The spider of chinese sex novel
Home-page: https://gitee.com/gan_jian_wen_main/first-edition-of-main-crawler
Author: ganjianwen
Author-email: 1727949032@qq.com
License: UNKNOWN
Platform: UNKNOWN
Classifier: Programming Language :: Python :: 3
Classifier: License :: OSI Approved :: MIT License
Classifier: Operating System :: OS Independent
Requires-Python: >=3.7
License-File: LICENSE.txt
Requires-Dist: lxml
Requires-Dist: bs4
Requires-Dist: requests
Requires-Dist: py3db
Requires-Dist: flask
Requires-Dist: zhconv
